marlin_data/__init__.py
marlin_data/marlin_data.py
marlindata-0.0.201.dist-info/LICENSE
marlindata-0.0.201.dist-info/METADATA
marlindata-0.0.201.dist-info/WHEEL
marlindata-0.0.201.dist-info/top_level.txt
marlindata-0.0.201.dist-info/RECORD
