Metadata-Version: 2.1
Name: marlindata
Version: 0.0.201
Summary: Marlin | Data Framework
Author: Rahul Tandon
Author-email: r.tandon@rsaqua.co.uk
Classifier: Programming Language :: Python :: 3
Classifier: License :: OSI Approved :: MIT License
Classifier: Operating System :: OS Independent
Requires-Python: >=3.7
License-File: LICENSE
